signing_clients/__init__.py
signing_clients/apps.py
signing_clients/constants.py
signing_clients/tests/__init__.py
signing_clients-1.5.0.dist-info/DESCRIPTION.rst
signing_clients-1.5.0.dist-info/METADATA
signing_clients-1.5.0.dist-info/RECORD
signing_clients-1.5.0.dist-info/WHEEL
signing_clients-1.5.0.dist-info/metadata.json
signing_clients-1.5.0.dist-info/top_level.txt
