Metadata-Version: 2.0
Name: signing-clients
Version: 1.5.0
Summary: Applications signature/manifest manipulator and receipt verifier
Home-page: https://github.com/mozilla/signing-clients/
Author: Ryan Tilder
Author-email: service-dev@mozilla.com
License: UNKNOWN
Keywords: web services
Platform: UNKNOWN
Classifier: Development Status :: 5 - Production/Stable
Classifier: Topic :: Security :: Cryptography
Classifier: Topic :: Software Development :: Libraries :: Python Modules
Classifier: Programming Language :: Python
Classifier: Operating System :: OS Independent
Classifier: Intended Audience :: Developers
Classifier: Programming Language :: Python
Classifier: Programming Language :: Python :: 2
Classifier: Programming Language :: Python :: 2.7
Classifier: Programming Language :: Python :: 3
Classifier: Programming Language :: Python :: 3.4
Classifier: Programming Language :: Python :: 3.5
Classifier: Programming Language :: Python :: 3.6
Classifier: Programming Language :: Python :: Implementation :: CPython
Requires-Dist: asn1crypto (>=0.23)
Requires-Dist: six (>=1.10.0)
